setup.py
torchrs/__init__.py
torchrs/__main__.py
torchrs/resolver.py
torchrs/util.py
torchrs.egg-info/PKG-INFO
torchrs.egg-info/SOURCES.txt
torchrs.egg-info/dependency_links.txt
torchrs.egg-info/top_level.txt
torchrs/git/__init__.py
torchrs/git/git.py
torchrs/logger/__init__.py
torchrs/logger/logger.py
torchrs/module/__init__.py
torchrs/module/module.py
torchrs/module/postprocess.py
torchrs/shell/__init__.py
torchrs/shell/shell.py