Metadata-Version: 1.0
Name: torchrs
Version: 0.2.3
Summary: Torch dependencies management tool
Home-page: UNKNOWN
Author: Binh Vu
Author-email: binh@toan2.com
License: PSF
Platform: UNKNOWN
